mil_kit/__init__.py
mil_kit/job.py
mil_kit/main.py
mil_kit/psd/__init__.py
mil_kit/psd/processor.py
mil_kit-0.4.5.dist-info/METADATA
mil_kit-0.4.5.dist-info/WHEEL
mil_kit-0.4.5.dist-info/entry_points.txt
mil_kit-0.4.5.dist-info/licenses/LICENSE
mil_kit-0.4.5.dist-info/RECORD
