Metadata-Version: 2.4
Name: mil-kit
Version: 0.4.5
Summary: A toolkit for processing the ASM's Mammal Image Library (MIL).
Project-URL: Homepage, https://github.com/hhandika/mil-kit
Project-URL: Repository, https://github.com/hhandika/mil-kit
Project-URL: Issues, https://github.com/hhandika/mil-kit/issues
Author-email: Heru Handika <herubiolog@gmail.com>
License: MIT
License-File: LICENSE
Keywords: automation,batch-processing,image-processing,photoshop,psd
Classifier: Development Status :: 4 - Beta
Classifier: Intended Audience :: Developers
Classifier: Intended Audience :: End Users/Desktop
Classifier: License :: OSI Approved :: MIT License
Classifier: Operating System :: OS Independent
Classifier: Programming Language :: Python :: 3
Classifier: Programming Language :: Python :: 3.10
Classifier: Programming Language :: Python :: 3.11
Classifier: Programming Language :: Python :: 3.12
Classifier: Topic :: Multimedia :: Graphics :: Graphics Conversion
Classifier: Topic :: Utilities
Requires-Python: >=3.10
Requires-Dist: pillow>=12.0.0
Requires-Dist: psd-tools>=1.12.0
Requires-Dist: tqdm>=4.67.1
